gsedit/__init__.py
gsedit/active-editor-theme.json
gsedit/active-theme.json
gsedit/cli.py
gsedit/code_completer.py
gsedit/css_editor.py
gsedit/custom_color_picker.py
gsedit/custom_mini_lexer.py
gsedit/custom_title_bar.py
gsedit/file_explorer.py
gsedit/grep.py
gsedit/grepgine.py
gsedit/gsconfig.json
gsedit/gsconfig.py
gsedit/integrated_terminal.py
gsedit/language_lexer.py
gsedit/main.py
gsedit/main_body.py
gsedit/menu_bar.py
gsedit/popup.py
gsedit/res_src.py
gsedit/runtime_qss.py
gsedit/sidebar.py
gsedit/status_bar.py
gsedit/tab_bar.py
gsedit/text_editor.py
gsedit/theme_editor.py
gsedit/themes_editor.py
gsedit/themes_editor_editor.py
gsedit/themes_editor_lexer.py
gsedit/tools.py
gsedit/top_bar.py
gsedit/vc.cp39-win_amd64.pyd
gsedit/version_control.py
gsedit/css/cssEditor.qss
gsedit/css/editorEditorRuleButton.qss
gsedit/css/editorEditorRuleLabel.qss
gsedit/css/editorEditorSaveButton.qss
gsedit/css/editorEditorTitle.qss
gsedit/css/editorViewTitleLabel.qss
gsedit/css/editorViewVersionLabel.qss
gsedit/css/grep.qss
gsedit/css/integratedTerminal.qss
gsedit/css/lexerCreatorTitle.qss
gsedit/css/lexerEditorRuleButton.qss
gsedit/css/lexerEditorRuleLabel.qss
gsedit/css/lexerEditorSaveButton.qss
gsedit/css/lexerEditorTitle.qss
gsedit/css/lexerViewFontLabel.qss
gsedit/css/lexerViewTitleLabel.qss
gsedit/css/lexerViewVersionLabel.qss
gsedit/css/listWidgetEditorThemes.qss
gsedit/css/listWidgetLexerThemes.qss
gsedit/css/mainBody.qss
gsedit/css/mainTabThemeEditor.qss
gsedit/css/mainWidgetThemeEditor.qss
gsedit/css/menuBar.qss
gsedit/css/saveButtonInactive.qss
gsedit/css/scrollAreaEditorThemes.qss
gsedit/css/scrollAreaLexerThemes.qss
gsedit/css/sidebar.qss
gsedit/css/statusBar.qss
gsedit/css/style.qss
gsedit/css/tabBar.qss
gsedit/css/themeBrowserSaveButton.qss
gsedit/css/themeEditor.qss
gsedit/css/themeEditorList.qss
gsedit/css/titleBarThemeEditor.qss
gsedit/css/tools.qss
gsedit/css/topBar.qss
gsedit/css/versionControl.qss
gsedit/images/add_icon.png
gsedit/images/close.svg
GS_Edit-0.2.6.dist-info/LICENSE
GS_Edit-0.2.6.dist-info/METADATA
GS_Edit-0.2.6.dist-info/WHEEL
GS_Edit-0.2.6.dist-info/entry_points.txt
GS_Edit-0.2.6.dist-info/top_level.txt
GS_Edit-0.2.6.dist-info/RECORD
