Metadata-Version: 2.1
Name: GS-Edit
Version: 0.2.6
Summary: The Best Code Editor - GS
Home-page: https://github.com/james-kaddissi/gsedit
Author: James Kaddissi
Author-email: jameskaddissi@gmail.com
Requires-Python: >=3.6
License-File: LICENSE
Requires-Dist: PyQt5
Requires-Dist: QScintilla
Requires-Dist: jedi
Requires-Dist: PyQt5-Frameless-Window
